pylprename/__init__.py
pylprename/transformer.py
pylprename-0.1.1.dist-info/DESCRIPTION.rst
pylprename-0.1.1.dist-info/METADATA
pylprename-0.1.1.dist-info/RECORD
pylprename-0.1.1.dist-info/WHEEL
pylprename-0.1.1.dist-info/metadata.json
pylprename-0.1.1.dist-info/top_level.txt
