Metadata-Version: 2.0
Name: pylprename
Version: 0.1.1
Summary: A Pylp plugin for renaming files in a stream
Home-page: https://github.com/pylp/pylprename
Author: Guillaume Gonnet
Author-email: gonnet.guillaume97@gmail.com
License: MIT
Keywords: pylp gulp rename
Platform: UNKNOWN
Classifier: Development Status :: 3 - Alpha
Classifier: Topic :: Utilities
Classifier: Topic :: Software Development :: Build Tools
Classifier: Framework :: AsyncIO
Classifier: Programming Language :: Python :: 3 :: Only
Classifier: Programming Language :: Python :: 3.5
Classifier: Intended Audience :: Developers
Classifier: Natural Language :: English
Classifier: License :: OSI Approved :: MIT License
Requires-Python: >=3.5
Requires-Dist: pylp
